pysparktools/__init__.py
pysparktools/aeshelper.py
pysparktools/hdfsloghandler.py
pysparktools/loghelper.py
pysparktools/sparkcleanhelper.py
pysparktools/sparkflattenhelper.py
pysparktools/sparkhdfshelper.py
pysparktools/sparkhelper.py
pysparktools/sparkjobbase1helper.py
pysparktools/sparkjobbase2helper.py
pysparktools/sparkjobbase3helper.py
pysparktools/sparkjobbase4helper.py
pysparktools/sparkjobbase5helper.py
pysparktools/sparkjobcurrenthelper.py
pysparktools/sparkjobflattenhelper.py
pysparktools/sparkjobhelper.py
pysparktools/sparkparquethelper.py
pysparktools/sparkparthelper.py
lkpysparktools-0.0.1.dist-info/METADATA
lkpysparktools-0.0.1.dist-info/WHEEL
lkpysparktools-0.0.1.dist-info/top_level.txt
lkpysparktools-0.0.1.dist-info/RECORD
