Metadata-Version: 2.1
Name: lkpysparktools
Version: 0.0.1
Requires-Dist: pycrypto
